django_bootstrap_input_group/__init__.py
django_bootstrap_input_group/renderers.py
django_bootstrap_input_group/static/django_bootstrap_input_group/css/bootstrap_input_group.css
django_bootstrap_input_group/templatetags/__init__.py
django_bootstrap_input_group/templatetags/django_bootstrap_input_group.py
django_bootstrap_input_group-1.0.1.dist-info/LICENSE
django_bootstrap_input_group-1.0.1.dist-info/METADATA
django_bootstrap_input_group-1.0.1.dist-info/WHEEL
django_bootstrap_input_group-1.0.1.dist-info/top_level.txt
django_bootstrap_input_group-1.0.1.dist-info/RECORD
