Metadata-Version: 2.1
Name: django-bootstrap-input-group
Version: 1.0.1
Summary: Render Django form fields as bootstrap input groups.
Author-email: Actionb <yummytea1@gmail.com>
License: MIT License
Project-URL: Repository, https://github.com/Actionb/django-bootstrap-input-group
Keywords: django,bootstrap
Classifier: Framework :: Django
Classifier: Programming Language :: Python
License-File: LICENSE
